ninjapy/__init__.py
ninjapy/auth.py
ninjapy/client.py
ninjapy/enums.py
ninjapy/exceptions.py
ninjapy/py.typed
ninjapy/types.py
ninjapy/utils.py
ninjapy-0.1.3.dist-info/licenses/LICENSE
ninjapy-0.1.3.dist-info/METADATA
ninjapy-0.1.3.dist-info/WHEEL
ninjapy-0.1.3.dist-info/top_level.txt
ninjapy-0.1.3.dist-info/RECORD
